{"id":"BRM_030","name":"Nefarian","type":"Minion","rarity":"Legendary","cost":9,"attack":8,"health":8,"text":"<b>Battlecry:<\/b> Add 2 random spells to your hand <i>(from your opponent's class)<\/i>.","flavor":"They call him \"Blackwing\" because he's a black dragon...... and he's got wings.","artist":"Ruan Jia","collectible":true,"elite":true,"race":"Dragon","howToGet":"Unlocked by defeating every boss in Blackrock Mountain!","howToGetGold":"Can be crafted after completing the Hidden Laboratory.","mechanics":["Battlecry"]}